aerospike.cpython-312-darwin.so
aerospike-18.1.0.dist-info/RECORD
aerospike-18.1.0.dist-info/WHEEL
aerospike-18.1.0.dist-info/top_level.txt
aerospike-18.1.0.dist-info/METADATA
aerospike-18.1.0.dist-info/licenses/LICENSE
aerospike_helpers/cdt_ctx.py
aerospike_helpers/__init__.py
aerospike_helpers/metrics/__init__.py
aerospike_helpers/operations/list_operations.py
aerospike_helpers/operations/map_operations.py
aerospike_helpers/operations/expression_operations.py
aerospike_helpers/operations/__init__.py
aerospike_helpers/operations/hll_operations.py
aerospike_helpers/operations/operations.py
aerospike_helpers/operations/bitwise_operations.py
aerospike_helpers/.dylibs/libssl.3.dylib
aerospike_helpers/.dylibs/libcrypto.3.dylib
aerospike_helpers/.dylibs/libyaml-0.2.dylib
aerospike_helpers/batch/records.py
aerospike_helpers/batch/__init__.py
aerospike_helpers/expressions/arithmetic.py
aerospike_helpers/expressions/bitwise.py
aerospike_helpers/expressions/list.py
aerospike_helpers/expressions/__init__.py
aerospike_helpers/expressions/map.py
aerospike_helpers/expressions/bitwise_operators.py
aerospike_helpers/expressions/resources.py
aerospike_helpers/expressions/hll.py
aerospike_helpers/expressions/base.py
aerospike-stubs/__init__.pyi
aerospike-stubs/exception.pyi
aerospike-stubs/predicates.pyi
aerospike-stubs/aerospike.pyi
