Metadata-Version: 2.4
Name: aerospike
Version: 18.1.0
Summary: Aerospike Client Library for Python
Author-email: "Aerospike, Inc." <info@aerospike.com>
License: Apache Software License
Project-URL: Homepage, https://aerospike.com
Keywords: aerospike,nosql,database
Classifier: License :: OSI Approved :: Apache Software License
Classifier: Operating System :: POSIX :: Linux
Classifier: Operating System :: MacOS :: MacOS X
Classifier: Operating System :: Microsoft :: Windows
Classifier: Programming Language :: Python :: 3.9
Classifier: Programming Language :: Python :: 3.10
Classifier: Programming Language :: Python :: 3.11
Classifier: Programming Language :: Python :: 3.12
Classifier: Programming Language :: Python :: 3.13
Classifier: Programming Language :: Python :: 3.14
Classifier: Programming Language :: Python :: Implementation :: CPython
Classifier: Topic :: Database
License-File: LICENSE
Dynamic: license-file
